deMultiplexer/__init__.py
deMultiplexer/deMultiplexer.py
jla_demultiplexer-0.0.8.dist-info/LICENSE
jla_demultiplexer-0.0.8.dist-info/METADATA
jla_demultiplexer-0.0.8.dist-info/WHEEL
jla_demultiplexer-0.0.8.dist-info/entry_points.txt
jla_demultiplexer-0.0.8.dist-info/top_level.txt
jla_demultiplexer-0.0.8.dist-info/RECORD
