Metadata-Version: 2.1
Name: jla-demultiplexer
Version: 0.0.8
Summary: Internal lab use tool for 3 end analysis
Home-page: https://github.com/TimNicholsonShaw/jla-demultiplexer
Author: Tim Nicholson-Shaw
Author-email: timnicholsonshaw@gmail.com
Project-URL: Lab Website, https://labs.biology.ucsd.edu/lykkeandersen/index.html
Keywords: Sequencing,ncRNAs,Bioinformatics
Classifier: Development Status :: 3 - Alpha
Classifier: License :: OSI Approved :: MIT License
Classifier: Programming Language :: Python :: 3 :: Only
Requires-Python: >=3.6
License-File: LICENSE
Requires-Dist: jla-tailer (>=0.1.5)
Requires-Dist: Affirmations (>=0.0.10)
Requires-Dist: pandas
Requires-Dist: distance
Requires-Dist: Bio
